pyenphase/__init__.py
pyenphase/auth.py
pyenphase/const.py
pyenphase/envoy.py
pyenphase/exceptions.py
pyenphase/firmware.py
pyenphase/json.py
pyenphase/models/__init__.py
pyenphase/models/acb.py
pyenphase/models/c6combiner.py
pyenphase/models/collar.py
pyenphase/models/common.py
pyenphase/models/dry_contacts.py
pyenphase/models/encharge.py
pyenphase/models/enpower.py
pyenphase/models/envoy.py
pyenphase/models/home.py
pyenphase/models/inverter.py
pyenphase/models/meters.py
pyenphase/models/storage_settings.py
pyenphase/models/system_consumption.py
pyenphase/models/system_production.py
pyenphase/models/tariff.py
pyenphase/py.typed
pyenphase/ssl.py
pyenphase/updaters/__init__.py
pyenphase/updaters/api_v1_production.py
pyenphase/updaters/api_v1_production_inverters.py
pyenphase/updaters/base.py
pyenphase/updaters/device_data_inverters.py
pyenphase/updaters/ensemble.py
pyenphase/updaters/generator.py
pyenphase/updaters/meters.py
pyenphase/updaters/production.py
pyenphase/updaters/tariff.py
pyenphase-2.4.3.dist-info/METADATA
pyenphase-2.4.3.dist-info/WHEEL
pyenphase-2.4.3.dist-info/licenses/LICENSE
pyenphase-2.4.3.dist-info/RECORD
